modbus_scale_ui/__init__.py
modbus_scale_ui/modbus_scale_ui.py
modbus_scale_ui/modbus_scale_ui.tcss
modbus_scale_ui-1.0.5.dist-info/licenses/LICENSE.md
modbus_scale_ui-1.0.5.dist-info/METADATA
modbus_scale_ui-1.0.5.dist-info/WHEEL
modbus_scale_ui-1.0.5.dist-info/top_level.txt
modbus_scale_ui-1.0.5.dist-info/RECORD
