Metadata-Version: 2.4
Name: modbus-scale-ui
Version: 1.0.5
Summary: Weigh scale Modbus Ethernet client user interface
Author-email: Rodney Elliott <rodney.elliott@canterbury.ac.nz>
License-Expression: GPL-3.0-or-later
Project-URL: Homepage, https://gitlab.com/uc_mech_wing/robotics_control_lab/uc-02-2024/modbus_scale_ui
Project-URL: Issues, https://gitlab.com/uc_mech_wing/robotics_control_lab/uc-02-2024/modbus_scale_ui/-/issues
Keywords: Modbus,Raspberry Pi,Scale
Classifier: Environment :: Console
Classifier: Intended Audience :: Developers
Classifier: Intended Audience :: Education
Classifier: Operating System :: OS Independent
Classifier: Programming Language :: Python :: 3
Requires-Python: >=3.9
License-File: LICENSE.md
Requires-Dist: modbus-scale-client>=1.1.0
Requires-Dist: textual==3.2.0
Requires-Dist: art==6.5
Requires-Dist: argparse>=1.4.0
Requires-Dist: ipaddress>=1.0.23
Dynamic: license-file
